[{"w":460.0,"class":"class circlesvssquares.Ground","h":1320.0,"y":201.0,"x":403.0},{"r":25.0,"class":"class circlesvssquares.EndPoint","y":240.0,"x":376.0},{"w":25.0,"class":"class circlesvssquares.Enemy","type":"Simple","h":25.0,"y":171.6,"x":355.8},{"w":25.0,"class":"class circlesvssquares.Enemy","type":"Simple","h":25.0,"y":171.4,"x":329.2},{"w":25.0,"class":"class circlesvssquares.Enemy","type":"Simple","h":25.0,"y":172.6,"x":300.2},{"w":25.0,"class":"class circlesvssquares.Enemy","type":"Simple","h":25.0,"y":172.0,"x":267.4},{"w":25.0,"class":"class circlesvssquares.Enemy","type":"Simple","h":25.0,"y":171.5,"x":230.7},{"w":25.0,"class":"class circlesvssquares.Enemy","type":"Simple","h":25.0,"y":170.9,"x":197.4},{"w":25.0,"class":"class circlesvssquares.Enemy","type":"Simple","h":25.0,"y":171.0,"x":167.0},{"w":25.0,"class":"class circlesvssquares.Enemy","type":"Simple","h":25.0,"y":171.0,"x":143.0},{"w":25.0,"class":"class circlesvssquares.Enemy","type":"Simple","h":25.0,"y":171.0,"x":116.0},{"w":25.0,"class":"class circlesvssquares.Enemy","type":"Simple","h":25.0,"y":171.0,"x":87.0},{"w":25.0,"class":"class circlesvssquares.Enemy","type":"Simple","h":25.0,"y":172.0,"x":68.0},{"w":3520.0,"class":"class circlesvssquares.Ground","h":800.0,"y":129.0,"x":208.0},{"w":3780.0,"class":"class circlesvssquares.Ground","h":270.0,"y":256.5,"x":191.0},{"w":130.0,"class":"class circlesvssquares.Ground","h":550.0,"y":250.5,"x":2.5},{"w":200.0,"class":"class circlesvssquares.Ground","h":1710.0,"y":147.5,"x":30.0},{"w":160.0,"class":"class circlesvssquares.Ground","h":1720.0,"y":146.0,"x":1.0},{"w":406.66663,"class":"class circlesvssquares.Ground","h":226.66664,"y":74.33333,"x":-23.666666},{"w":436.66663,"class":"class circlesvssquares.Ground","h":130.0,"y":46.5,"x":14.5},{"w":133.3333,"class":"class circlesvssquares.Ground","h":650.0,"y":47.166664,"x":37.0},{"w":25.0,"class":"class circlesvssquares.Enemy","type":"Simple","h":25.0,"y":25.333332,"x":27.333332},{"w":25.0,"class":"class circlesvssquares.Enemy","type":"Simple","h":25.0,"y":24.0,"x":-14.666667},{"w":303.3333,"class":"class circlesvssquares.Ground","h":263.3333,"y":10.833333,"x":28.499998},{"w":420.0,"class":"class circlesvssquares.Ground","h":99.99999,"y":17.666666,"x":-15.0},{"w":380.0,"class":"class circlesvssquares.Ground","h":886.6666,"y":19.666668,"x":-50.0},{"w":745.7142,"class":"class circlesvssquares.Ground","h":332.85712,"y":-8.785713,"x":6.2857094}]